transito/__init__.py
transito/edn.py
transito/transito.py
transito-0.1.6.dist-info/DESCRIPTION.rst
transito-0.1.6.dist-info/METADATA
transito-0.1.6.dist-info/RECORD
transito-0.1.6.dist-info/WHEEL
transito-0.1.6.dist-info/entry_points.txt
transito-0.1.6.dist-info/metadata.json
transito-0.1.6.dist-info/top_level.txt
