Metadata-Version: 2.0
Name: transito
Version: 0.1.6
Summary: Command Line Tool to Work with Transit Format
Home-page: https://github.com/marianoguerra/transito
Author: Mariano Guerra
Author-email: luismarianoguerra@gmail.com
License: ISCL
Keywords: transito
Platform: UNKNOWN
Classifier: Development Status :: 2 - Pre-Alpha
Classifier: Intended Audience :: Developers
Classifier: License :: OSI Approved :: ISC License (ISCL)
Classifier: Natural Language :: English
Classifier: Programming Language :: Python :: 2
Classifier: Programming Language :: Python :: 2.6
Classifier: Programming Language :: Python :: 2.7
Requires-Dist: requests
Requires-Dist: rply
Requires-Dist: transit-python
